taxonomy_synthesis/__init__.py
taxonomy_synthesis/classifiers/__init__.py
taxonomy_synthesis/classifiers/classifier_interface.py
taxonomy_synthesis/classifiers/embedding_classifier.py
taxonomy_synthesis/classifiers/gpt_classifier.py
taxonomy_synthesis/generator/__init__.py
taxonomy_synthesis/generator/taxonomy_generator.py
taxonomy_synthesis/models/__init__.py
taxonomy_synthesis/models/category.py
taxonomy_synthesis/models/classified_item.py
taxonomy_synthesis/models/item.py
taxonomy_synthesis/models/response_item.py
taxonomy_synthesis/tree/__init__.py
taxonomy_synthesis/tree/node_operator.py
taxonomy_synthesis/tree/tree_node.py
taxonomy_synthesis-0.1.9.dist-info/LICENSE
taxonomy_synthesis-0.1.9.dist-info/METADATA
taxonomy_synthesis-0.1.9.dist-info/WHEEL
taxonomy_synthesis-0.1.9.dist-info/RECORD
