Metadata-Version: 2.1
Name: taxonomy-synthesis
Version: 0.1.9
Summary: An AI-driven framework for synthesizing adaptive taxonomies, enabling automated data categorization and classification within dynamic hierarchical structures.
Author: Sebastian Sosa
Author-email: 1sebastian1sosa1@gmail.com> @ OPENGPT LLC <https://opengpt.llc/
Requires-Python: >=3.9,<4.0
Classifier: Programming Language :: Python :: 3
Classifier: Programming Language :: Python :: 3.9
Classifier: Programming Language :: Python :: 3.10
Classifier: Programming Language :: Python :: 3.11
Classifier: Programming Language :: Python :: 3.12
Classifier: Programming Language :: Python :: 3.13
Requires-Dist: openai (>=1.42.0,<2.0.0)
Requires-Dist: pydantic (>=2.8.2,<3.0.0)
